cxxfilt/__init__.py
cxxfilt/version.py
cxxfilt-0.3.0.dist-info/LICENSE
cxxfilt-0.3.0.dist-info/METADATA
cxxfilt-0.3.0.dist-info/WHEEL
cxxfilt-0.3.0.dist-info/top_level.txt
cxxfilt-0.3.0.dist-info/RECORD
