Metadata-Version: 2.1
Name: cxxfilt
Version: 0.3.0
Summary: Python interface to c++filt / abi::__cxa_demangle
Home-page: https://github.com/afq984/python-cxxfilt
Author: afq984
Author-email: afg984@gmail.com
License: BSD
Keywords: c++ c++filt name mangling
Platform: UNKNOWN
Classifier: Development Status :: 3 - Alpha
Classifier: Intended Audience :: Developers
Classifier: Topic :: Software Development :: Build Tools
Classifier: License :: OSI Approved :: BSD License
Classifier: Programming Language :: Python :: 3 :: Only
Classifier: Programming Language :: Python :: 3
Classifier: Programming Language :: Python :: 3.6
Classifier: Programming Language :: Python :: 3.7
Classifier: Programming Language :: Python :: 3.8
Classifier: Programming Language :: Python :: 3.9
Provides-Extra: test
